{
  "project_info": {
    "project_number": "506582818449",
    "firebase_url": "https://ticker-d5222.firebaseio.com",
    "project_id": "ticker-d5222",
    "storage_bucket": "ticker-d5222.appspot.com"
  },
  "client": [
    {
      "client_info": {
        "mobilesdk_app_id": "1:506582818449:android:57fd1d56e08c167d",
        "android_client_info": {
          "package_name": "jajodia.aditya.com.bunkmanager2"
        }
      },
      "oauth_client": [
        {
          "client_id": "506582818449-cr5mmrek892u3rurcm55k4lio001l7tg.apps.googleusercontent.com",
          "client_type": 3
        }
      ],
      "api_key": [
        {
          "current_key": "AIzaSyBEgoc5OpCXEa9NQtDe3q9v-LvIxTUCe68"
        }
      ],
      "services": {
        "analytics_service": {
          "status": 1
        },
        "appinvite_service": {
          "status": 1,
          "other_platform_oauth_client": []
        },
        "ads_service": {
          "status": 2
        }
      }
    },
    {
      "client_info": {
        "mobilesdk_app_id": "1:506582818449:android:058ee93c12bcdfc8",
        "android_client_info": {
          "package_name": "jajodia.aditya.com.tickernotify"
        }
      },
      "oauth_client": [
        {
          "client_id": "506582818449-cr5mmrek892u3rurcm55k4lio001l7tg.apps.googleusercontent.com",
          "client_type": 3
        }
      ],
      "api_key": [
        {
          "current_key": "AIzaSyBEgoc5OpCXEa9NQtDe3q9v-LvIxTUCe68"
        }
      ],
      "services": {
        "analytics_service": {
          "status": 1
        },
        "appinvite_service": {
          "status": 1,
          "other_platform_oauth_client": []
        },
        "ads_service": {
          "status": 2
        }
      }
    }
  ],
  "configuration_version": "1"
}